LICENSE
MANIFEST.in
README.rst
setup.cfg
setup.py
runtime_context/__init__.py
runtime_context/env.py
runtime_context/runtime_context.py
runtime_context.egg-info/PKG-INFO
runtime_context.egg-info/SOURCES.txt
runtime_context.egg-info/dependency_links.txt
runtime_context.egg-info/requires.txt
runtime_context.egg-info/top_level.txt
tests/__init__.py
tests/conftest.py
tests/test_env.py
tests/test_runtime_context.py