Metadata-Version: 1.1
Name: runtime-context
Version: 2.0.0
Summary: Runtime context
Home-page: https://github.com/jbasko/runtime-context
Author: Jazeps Basko
Author-email: jazeps.basko@gmail.com
License: MIT
Platform: UNKNOWN
Classifier: Development Status :: 4 - Beta
Classifier: Intended Audience :: Developers
Classifier: Programming Language :: Python
Classifier: Programming Language :: Python :: 3
Classifier: Programming Language :: Python :: 3.5
Classifier: Programming Language :: Python :: 3.6
Classifier: License :: OSI Approved :: MIT License
